[
null,
{"id":1,"list":[{"code":242,"indent":0,"parameters":[3]},{"code":230,"indent":0,"parameters":[180]},{"code":121,"indent":0,"parameters":[6,6,1]},{"code":122,"indent":0,"parameters":[50,50,1,0,1]},{"code":201,"indent":0,"parameters":[0,16,2,3,0,0]},{"code":222,"indent":0,"parameters":[]},{"code":241,"indent":0,"parameters":[{"name":"Track No 5 by Marcel Martinus","volume":100,"pitch":100,"pan":0}]},{"code":101,"indent":0,"parameters":["",0,0,2]},{"code":401,"indent":0,"parameters":["<After a good rest, you are full of energy again>\\!"]},{"code":401,"indent":0,"parameters":["<Today is March \\v[50],\\. but you shouldn't worry"]},{"code":401,"indent":0,"parameters":["too much and live today the fullest>"]},{"code":0,"indent":0,"parameters":[]}],"name":"to day","switchId":6,"trigger":0},
{"id":2,"list":[{"code":242,"indent":0,"parameters":[3]},{"code":230,"indent":0,"parameters":[60]},{"code":121,"indent":0,"parameters":[6,6,0]},{"code":201,"indent":0,"parameters":[0,16,3,5,0,0]},{"code":222,"indent":0,"parameters":[]},{"code":241,"indent":0,"parameters":[{"name":"Track No 4 by Marcel Martinus","volume":100,"pitch":100,"pan":0}]},{"code":101,"indent":0,"parameters":["",0,0,2]},{"code":401,"indent":0,"parameters":["<It's evening and you've finished dinner>\\!"]},{"code":401,"indent":0,"parameters":["<You can go to bed or wander around the town>\\!"]},{"code":0,"indent":0,"parameters":[]}],"name":"to night","switchId":1,"trigger":0},
{"id":3,"list":[{"code":242,"indent":0,"parameters":[3]},{"code":230,"indent":0,"parameters":[180]},{"code":243,"indent":0,"parameters":[]},{"code":241,"indent":0,"parameters":[{"name":"Track No 1 by Marcel Martinus","volume":100,"pitch":100,"pan":0}]},{"code":0,"indent":0,"parameters":[]}],"name":"Change music - Upbeat","switchId":1,"trigger":0},
{"id":4,"list":[{"code":242,"indent":0,"parameters":[3]},{"code":230,"indent":0,"parameters":[180]},{"code":243,"indent":0,"parameters":[]},{"code":241,"indent":0,"parameters":[{"name":"Track No 2 by Marcel Martinus","volume":100,"pitch":100,"pan":0}]},{"code":0,"indent":0,"parameters":[]}],"name":"Change music - Night","switchId":1,"trigger":0},
{"id":5,"list":[{"code":242,"indent":0,"parameters":[3]},{"code":230,"indent":0,"parameters":[180]},{"code":243,"indent":0,"parameters":[]},{"code":241,"indent":0,"parameters":[{"name":"Track No 3 by Marcel Martinus","volume":100,"pitch":100,"pan":0}]},{"code":0,"indent":0,"parameters":[]}],"name":"Change music - Neutral-","switchId":1,"trigger":0},
{"id":6,"list":[{"code":242,"indent":0,"parameters":[3]},{"code":230,"indent":0,"parameters":[180]},{"code":243,"indent":0,"parameters":[]},{"code":241,"indent":0,"parameters":[{"name":"Track No 6 by Marcel Martinus","volume":100,"pitch":100,"pan":0}]},{"code":0,"indent":0,"parameters":[]}],"name":"Change music - Sad","switchId":1,"trigger":0},
{"id":7,"list":[{"code":242,"indent":0,"parameters":[3]},{"code":230,"indent":0,"parameters":[180]},{"code":244,"indent":0,"parameters":[]},{"code":0,"indent":0,"parameters":[]}],"name":"Replay music","switchId":1,"trigger":0},
{"id":8,"list":[{"code":122,"indent":0,"parameters":[10,10,1,0,1]},{"code":241,"indent":0,"parameters":[{"name":"Track No 6 by Marcel Martinus","volume":100,"pitch":100,"pan":0}]},{"code":111,"indent":0,"parameters":[1,10,0,1,0]},{"code":101,"indent":1,"parameters":["",0,2,1]},{"code":401,"indent":1,"parameters":["<A story suddenly pops in your mind>\\."]},{"code":401,"indent":1,"parameters":["<You are unable to recall from where is it from>"]},{"code":101,"indent":1,"parameters":["",0,2,1]},{"code":401,"indent":1,"parameters":["The title of the particular story is \"Tale of the Mighty Demon\""]},{"code":101,"indent":1,"parameters":["",0,2,1]},{"code":401,"indent":1,"parameters":["Once upon a time...\\."]},{"code":401,"indent":1,"parameters":["In the deepest of hell,\\. there lived a big demon.\\|"]},{"code":401,"indent":1,"parameters":["He is strong,\\. dependable,\\. and everybody rely on him."]},{"code":101,"indent":1,"parameters":["",0,2,1]},{"code":401,"indent":1,"parameters":["\"Hey, help us build a new storage\" A demon asked.\\|"]},{"code":401,"indent":1,"parameters":["\"Help us hunting\" Another demon showed up.\\|"]},{"code":401,"indent":1,"parameters":["\"Can you patrol this night?\" Said yet another demon.\\|"]},{"code":101,"indent":1,"parameters":["",0,2,1]},{"code":401,"indent":1,"parameters":["More and more demons show up, just to ask for help.\\."]},{"code":401,"indent":1,"parameters":["This special demon is blessed with enormous amount"]},{"code":401,"indent":1,"parameters":["of strength, hence all their problems solved."]},{"code":101,"indent":1,"parameters":["",0,2,1]},{"code":401,"indent":1,"parameters":["<It's all you can remember for now>"]},{"code":0,"indent":1,"parameters":[]},{"code":411,"indent":0,"parameters":[]},{"code":111,"indent":1,"parameters":[1,10,0,2,0]},{"code":101,"indent":2,"parameters":["",0,2,1]},{"code":401,"indent":2,"parameters":["<A story suddenly pops in your mind>\\."]},{"code":401,"indent":2,"parameters":["<It is the continuation of the last piece>"]},{"code":101,"indent":2,"parameters":["",0,2,1]},{"code":401,"indent":2,"parameters":["One day, in the middle of his hunting, he encountered a"]},{"code":401,"indent":2,"parameters":["small angel. \\|She was wounded,\\. writhing in pain,\\. having her"]},{"code":401,"indent":2,"parameters":["wings scattered into pieces."]},{"code":101,"indent":2,"parameters":["",0,2,1]},{"code":401,"indent":2,"parameters":["She shouldn't be in hell,\\. yet she doesn't want to went back"]},{"code":401,"indent":2,"parameters":["to heaven either.\\. As heaven is the source of her sufferings."]},{"code":401,"indent":2,"parameters":["A place full of light, as well as shadows."]},{"code":101,"indent":2,"parameters":["",0,2,1]},{"code":401,"indent":2,"parameters":["The demon kneeled down so he can see her eyes clearly.\\.\\."]},{"code":401,"indent":2,"parameters":["An emerald eyes, full of despair,\\. as if she doesn't know"]},{"code":401,"indent":2,"parameters":["how she is still alive,\\. despite of wanting to begone forever."]},{"code":101,"indent":2,"parameters":["",0,2,1]},{"code":401,"indent":2,"parameters":["...\\.\\."]},{"code":401,"indent":2,"parameters":["Without saying anything,\\. the demon carried the angel"]},{"code":401,"indent":2,"parameters":["on his back,\\. then walked to his home slowly."]},{"code":101,"indent":2,"parameters":["",0,2,1]},{"code":401,"indent":2,"parameters":["<You are still unable to remember where is it from>"]},{"code":0,"indent":2,"parameters":[]},{"code":411,"indent":1,"parameters":[]},{"code":111,"indent":2,"parameters":[1,10,0,3,0]},{"code":101,"indent":3,"parameters":["",0,2,1]},{"code":401,"indent":3,"parameters":["<A story suddenly pops in your mind>\\."]},{"code":401,"indent":3,"parameters":["<It is the continuation of the last piece>"]},{"code":101,"indent":3,"parameters":["",0,2,1]},{"code":401,"indent":3,"parameters":["The angel lived with the mighty demon.\\. She would take care"]},{"code":401,"indent":3,"parameters":["of things the demon wouldn't care about :\\. himself."]},{"code":101,"indent":3,"parameters":["",0,2,1]},{"code":401,"indent":3,"parameters":["From heating the bath so it's in ideal temperature, \\."]},{"code":401,"indent":3,"parameters":["cooking foods that is enjoyable, not just consumable,\\."]},{"code":401,"indent":3,"parameters":["even she would give the demon all the praises he deserved."]},{"code":101,"indent":3,"parameters":["",0,2,1]},{"code":401,"indent":3,"parameters":["They enjoyed their lives,\\. though from two different worlds.\\|"]},{"code":401,"indent":3,"parameters":["But,\\. everything is the opposite for other demons."]},{"code":101,"indent":3,"parameters":["",0,2,1]},{"code":401,"indent":3,"parameters":["They want more attention,\\. though only ever think of themself.\\|"]},{"code":401,"indent":3,"parameters":["They want more service,\\. as if they are the owner of the hell.\\|"]},{"code":401,"indent":3,"parameters":["They want everything,\\. though never giving anything."]},{"code":101,"indent":3,"parameters":["",0,2,1]},{"code":401,"indent":3,"parameters":["<You are still unable to remember where is it from>"]},{"code":0,"indent":3,"parameters":[]},{"code":411,"indent":2,"parameters":[]},{"code":111,"indent":3,"parameters":[1,10,0,4,0]},{"code":101,"indent":4,"parameters":["",0,2,1]},{"code":401,"indent":4,"parameters":["<A story suddenly pops in your mind>\\."]},{"code":401,"indent":4,"parameters":["<It is the continuation of the last piece>"]},{"code":101,"indent":4,"parameters":["",0,2,1]},{"code":401,"indent":4,"parameters":["The demons plotted a 'revenge' for the mighty demon, \\."]},{"code":401,"indent":4,"parameters":["for not abiding to their words,\\. for staying beside"]},{"code":401,"indent":4,"parameters":["the angel's side."]},{"code":101,"indent":4,"parameters":["",0,2,1]},{"code":401,"indent":4,"parameters":["\"Should we bully the angel?\"\\|"]},{"code":401,"indent":4,"parameters":["An idea comes up,\\. fuelled with their hatred,\\. or maybe"]},{"code":401,"indent":4,"parameters":["envy towards the angel."]},{"code":101,"indent":4,"parameters":["",0,2,1]},{"code":401,"indent":4,"parameters":["Other demons agreed.\\.\\. They thought the angel deserve"]},{"code":401,"indent":4,"parameters":["nothing but sadness.\\.\\. Happiness is theirs to own, \\.nobody"]},{"code":401,"indent":4,"parameters":["else should have it, even the mighty demon."]},{"code":101,"indent":4,"parameters":["",0,2,1]},{"code":401,"indent":4,"parameters":["Blinded with meaningless emotion, they started to"]},{"code":401,"indent":4,"parameters":["secretly torture the helpless angel, threatening her"]},{"code":401,"indent":4,"parameters":["to crush both their lives if she tells the mighty demon."]},{"code":101,"indent":4,"parameters":["",0,2,1]},{"code":401,"indent":4,"parameters":["...After some time, they realized...\\|"]},{"code":401,"indent":4,"parameters":["Realized how fun stomping on someone is."]},{"code":101,"indent":4,"parameters":["",0,2,1]},{"code":401,"indent":4,"parameters":["<You are still unable to remember where is it from>"]},{"code":0,"indent":4,"parameters":[]},{"code":411,"indent":3,"parameters":[]},{"code":111,"indent":4,"parameters":[1,10,0,5,0]},{"code":101,"indent":5,"parameters":["",0,2,1]},{"code":401,"indent":5,"parameters":["<A story suddenly pops in your mind>\\."]},{"code":401,"indent":5,"parameters":["<It is the continuation of the last piece>"]},{"code":101,"indent":5,"parameters":["",0,2,1]},{"code":401,"indent":5,"parameters":["<You are still unable to remember where is it from>"]},{"code":0,"indent":5,"parameters":[]},{"code":411,"indent":4,"parameters":[]},{"code":111,"indent":5,"parameters":[1,10,0,6,0]},{"code":101,"indent":6,"parameters":["",0,2,1]},{"code":401,"indent":6,"parameters":["<A story suddenly pops in your mind>\\."]},{"code":401,"indent":6,"parameters":["<It is the continuation of the last piece>"]},{"code":101,"indent":6,"parameters":["",0,2,1]},{"code":401,"indent":6,"parameters":["<You are still unable to remember where is it from>"]},{"code":0,"indent":6,"parameters":[]},{"code":411,"indent":5,"parameters":[]},{"code":0,"indent":6,"parameters":[]},{"code":412,"indent":5,"parameters":[]},{"code":0,"indent":5,"parameters":[]},{"code":412,"indent":4,"parameters":[]},{"code":0,"indent":4,"parameters":[]},{"code":412,"indent":3,"parameters":[]},{"code":0,"indent":3,"parameters":[]},{"code":412,"indent":2,"parameters":[]},{"code":0,"indent":2,"parameters":[]},{"code":412,"indent":1,"parameters":[]},{"code":0,"indent":1,"parameters":[]},{"code":412,"indent":0,"parameters":[]},{"code":0,"indent":0,"parameters":[]}],"name":"Tales of the Mighty Demon","switchId":1,"trigger":0}
]